maracatu/__init__.py
maracatu/notebook/__init__.py
maracatu/src/__init__.py
maracatu/src/base/__init__.py
maracatu/src/base/curves.py
maracatu/src/base/error_bar.py
maracatu/src/base/parameters.py
maracatu/src/base/plot_base.py
maracatu/src/base/scatter.py
maracatu/src/plotting/__init__.py
maracatu/src/plotting/curves.py
maracatu/src/plotting/error_bar.py
maracatu/src/plotting/heatmap.py
maracatu/src/plotting/plot_base.py
maracatu/src/plotting/scatter.py
maracatu/src/statistics/__init__.py
maracatu/src/statistics/difference.py
maracatu/src/statistics/base/__init__.py
maracatu/src/statistics/base/bins.py
maracatu/src/statistics/base/confidence_inverval.py
maracatu/src/statistics/base/correlation.py
maracatu/src/statistics/base/joints.py
maracatu/src/statistics/base/survival.py
maracatu-1.0.12.dist-info/METADATA
maracatu-1.0.12.dist-info/WHEEL
maracatu-1.0.12.dist-info/top_level.txt
maracatu-1.0.12.dist-info/RECORD
