Metadata-Version: 2.1
Name: maracatu
Version: 1.0.12
Summary: Maracatu is a plotting package
Home-page: https://github.com/diegompin/maracatu
Author: Diego Pinheiro
Author-email: diegompin@gmail.com
License: UNKNOWN
Platform: UNKNOWN
Requires-Dist: pandas
Requires-Dist: matplotlib
Requires-Dist: numpy
